sec_edgar_toolkit/__init__.py
sec_edgar_toolkit/edgar.py
sec_edgar_toolkit/client/__init__.py
sec_edgar_toolkit/client/sec_edgar_api.py
sec_edgar_toolkit/core/__init__.py
sec_edgar_toolkit/core/company.py
sec_edgar_toolkit/core/filing.py
sec_edgar_toolkit/core/global_functions.py
sec_edgar_toolkit/core/xbrl.py
sec_edgar_toolkit/endpoints/__init__.py
sec_edgar_toolkit/endpoints/company.py
sec_edgar_toolkit/endpoints/filings.py
sec_edgar_toolkit/endpoints/xbrl.py
sec_edgar_toolkit/exceptions/__init__.py
sec_edgar_toolkit/exceptions/base.py
sec_edgar_toolkit/exceptions/http.py
sec_edgar_toolkit/parsers/__init__.py
sec_edgar_toolkit/parsers/current_events.py
sec_edgar_toolkit/parsers/financial_forms.py
sec_edgar_toolkit/parsers/item_extractor.py
sec_edgar_toolkit/parsers/ownership_forms.py
sec_edgar_toolkit/types/__init__.py
sec_edgar_toolkit/types/analytics.py
sec_edgar_toolkit/types/company.py
sec_edgar_toolkit/types/current_events.py
sec_edgar_toolkit/types/filing.py
sec_edgar_toolkit/types/financial_forms.py
sec_edgar_toolkit/types/institutional_holdings.py
sec_edgar_toolkit/types/parsing.py
sec_edgar_toolkit/types/proxy_statements.py
sec_edgar_toolkit/utils/__init__.py
sec_edgar_toolkit/utils/filters.py
sec_edgar_toolkit/utils/http.py
sec_edgar_toolkit/utils/xml_parser.py
sec_edgar_toolkit-0.1.1.dist-info/METADATA
sec_edgar_toolkit-0.1.1.dist-info/WHEEL
sec_edgar_toolkit-0.1.1.dist-info/top_level.txt
sec_edgar_toolkit-0.1.1.dist-info/RECORD
