Metadata-Version: 2.4
Name: sec-edgar-toolkit
Version: 0.1.1
Summary: Open source toolkit to facilitate working with the SEC EDGAR database
Author-email: Stefano Amorelli <stefano@amorelli.tech>
License: AGPL-3.0
Project-URL: Homepage, https://github.com/stefanoamorelli/sec-edgar-toolkit
Project-URL: Documentation, https://github.com/stefanoamorelli/sec-edgar-toolkit#readme
Project-URL: Repository, https://github.com/stefanoamorelli/sec-edgar-toolkit.git
Project-URL: Issues, https://github.com/stefanoamorelli/sec-edgar-toolkit/issues
Keywords: SEC,EDGAR,finance,filings,10-K,10-Q,8-K,securities
Classifier: Development Status :: 3 - Alpha
Classifier: Intended Audience :: Developers
Classifier: Intended Audience :: Financial and Insurance Industry
Classifier: License :: OSI Approved :: GNU Affero General Public License v3
Classifier: Programming Language :: Python :: 3
Classifier: Programming Language :: Python :: 3.8
Classifier: Programming Language :: Python :: 3.9
Classifier: Programming Language :: Python :: 3.10
Classifier: Programming Language :: Python :: 3.11
Classifier: Programming Language :: Python :: 3.12
Classifier: Topic :: Office/Business :: Financial
Classifier: Topic :: Software Development :: Libraries :: Python Modules
Requires-Python: >=3.8
Requires-Dist: requests>=2.31.0
Requires-Dist: beautifulsoup4>=4.12.0
Requires-Dist: lxml>=4.9.0
Requires-Dist: pandas>=2.0.0
Provides-Extra: dev
Requires-Dist: pytest>=7.4.0; extra == "dev"
Requires-Dist: pytest-cov>=4.1.0; extra == "dev"
Requires-Dist: pytest-asyncio>=0.21.0; extra == "dev"
Requires-Dist: black>=23.7.0; extra == "dev"
Requires-Dist: ruff>=0.1.0; extra == "dev"
Requires-Dist: mypy>=1.5.0; extra == "dev"
Requires-Dist: types-requests>=2.31.0; extra == "dev"
Requires-Dist: pre-commit>=3.3.0; extra == "dev"
Requires-Dist: responses>=0.24.0; extra == "dev"
